[
    {
        "old_api": "gitdb.fun.PY3",
        "new_api": "",
        "old_parameter": {},
        "new_parameter": {},
        "old_type": "module_field",
        "new_type": "",
        "change_type": "api_removal",
        "IC": "FIC"
    },
    {
        "old_api": "gitdb.loose.MAXSIZE",
        "new_api": "",
        "old_parameter": {},
        "new_parameter": {},
        "old_type": "module_field",
        "new_type": "",
        "change_type": "api_removal",
        "IC": "FIC"
    },
    {
        "old_api": "gitdb.stream.PY26",
        "new_api": "",
        "old_parameter": {},
        "new_parameter": {},
        "old_type": "module_field",
        "new_type": "",
        "change_type": "api_removal",
        "IC": "FIC"
    },
    {
        "old_api": "gitdb.db.loose.MAXSIZE",
        "new_api": "",
        "old_parameter": {},
        "new_parameter": {},
        "old_type": "module_field",
        "new_type": "",
        "change_type": "api_removal",
        "IC": "FIC"
    },
    {
        "old_api": "gitdb.test.lib.skip_on_travis_ci",
        "new_api": "",
        "old_parameter": {
            "func": {
                "description": null,
                "is_optional": false
            }
        },
        "new_parameter": {},
        "old_type": "function",
        "new_type": "",
        "change_type": "api_removal",
        "IC": "FIC"
    },
    {
        "old_api": "gitdb.test.test_pack.TestPack.__call__",
        "new_api": "",
        "old_parameter": {
            "self": {
                "description": null,
                "is_optional": false
            },
            "args": {
                "description": null,
                "is_optional": false
            },
            "kwds": {
                "description": null,
                "is_optional": false
            }
        },
        "new_parameter": {},
        "old_type": "member_function",
        "new_type": "",
        "change_type": "api_removal",
        "IC": "FIC"
    },
    {
        "old_api": "gitdb.test.test_pack.TestPack.__eq__",
        "new_api": "",
        "old_parameter": {
            "self": {
                "description": null,
                "is_optional": false
            },
            "other": {
                "description": null,
                "is_optional": false
            }
        },
        "new_parameter": {},
        "old_type": "member_function",
        "new_type": "",
        "change_type": "api_removal",
        "IC": "FIC"
    },
    {
        "old_api": "gitdb.test.test_pack.TestPack.__hash__",
        "new_api": "",
        "old_parameter": {
            "self": {
                "description": null,
                "is_optional": false
            }
        },
        "new_parameter": {},
        "old_type": "member_function",
        "new_type": "",
        "change_type": "api_removal",
        "IC": "FIC"
    },
    {
        "old_api": "gitdb.test.test_pack.TestPack.__init__",
        "new_api": "",
        "old_parameter": {
            "self": {
                "description": null,
                "is_optional": false
            },
            "methodName": {
                "description": null,
                "is_optional": true
            }
        },
        "new_parameter": {},
        "old_type": "member_function",
        "new_type": "",
        "change_type": "api_removal",
        "IC": "FIC"
    },
    {
        "old_api": "gitdb.test.test_pack.TestPack.__repr__",
        "new_api": "",
        "old_parameter": {
            "self": {
                "description": null,
                "is_optional": false
            }
        },
        "new_parameter": {},
        "old_type": "member_function",
        "new_type": "",
        "change_type": "api_removal",
        "IC": "FIC"
    },
    {
        "old_api": "gitdb.test.test_pack.TestPack.__str__",
        "new_api": "",
        "old_parameter": {
            "self": {
                "description": null,
                "is_optional": false
            }
        },
        "new_parameter": {},
        "old_type": "member_function",
        "new_type": "",
        "change_type": "api_removal",
        "IC": "FIC"
    },
    {
        "old_api": "gitdb.test.test_pack.TestPack.addCleanup",
        "new_api": "",
        "old_parameter": {
            "self": {
                "description": null,
                "is_optional": false
            },
            "function": {
                "description": null,
                "is_optional": false
            },
            "args": {
                "description": null,
                "is_optional": false
            },
            "kwargs": {
                "description": null,
                "is_optional": false
            }
        },
        "new_parameter": {},
        "old_type": "member_function",
        "new_type": "",
        "change_type": "api_removal",
        "IC": "FIC"
    },
    {
        "old_api": "gitdb.test.test_pack.TestPack.addTypeEqualityFunc",
        "new_api": "",
        "old_parameter": {
            "self": {
                "description": null,
                "is_optional": false
            },
            "typeobj": {
                "description": null,
                "is_optional": false
            },
            "function": {
                "description": null,
                "is_optional": false
            }
        },
        "new_parameter": {},
        "old_type": "member_function",
        "new_type": "",
        "change_type": "api_removal",
        "IC": "FIC"
    },
    {
        "old_api": "gitdb.test.test_pack.TestPack.assertAlmostEqual",
        "new_api": "",
        "old_parameter": {
            "self": {
                "description": null,
                "is_optional": false
            },
            "first": {
                "description": null,
                "is_optional": false
            },
            "second": {
                "description": null,
                "is_optional": false
            },
            "places": {
                "description": null,
                "is_optional": true
            },
            "msg": {
                "description": null,
                "is_optional": true
            },
            "delta": {
                "description": null,
                "is_optional": true
            }
        },
        "new_parameter": {},
        "old_type": "member_function",
        "new_type": "",
        "change_type": "api_removal",
        "IC": "FIC"
    },
    {
        "old_api": "gitdb.test.test_pack.TestPack.assertAlmostEquals",
        "new_api": "",
        "old_parameter": {
            "args": {
                "description": null,
                "is_optional": false
            },
            "kwargs": {
                "description": null,
                "is_optional": false
            }
        },
        "new_parameter": {},
        "old_type": "member_function",
        "new_type": "",
        "change_type": "api_removal",
        "IC": "FIC"
    },
    {
        "old_api": "gitdb.test.test_pack.TestPack.assertCountEqual",
        "new_api": "",
        "old_parameter": {
            "self": {
                "description": null,
                "is_optional": false
            },
            "first": {
                "description": null,
                "is_optional": false
            },
            "second": {
                "description": null,
                "is_optional": false
            },
            "msg": {
                "description": null,
                "is_optional": true
            }
        },
        "new_parameter": {},
        "old_type": "member_function",
        "new_type": "",
        "change_type": "api_removal",
        "IC": "FIC"
    },
    {
        "old_api": "gitdb.test.test_pack.TestPack.assertDictContainsSubset",
        "new_api": "",
        "old_parameter": {
            "self": {
                "description": null,
                "is_optional": false
            },
            "subset": {
                "description": null,
                "is_optional": false
            },
            "dictionary": {
                "description": null,
                "is_optional": false
            },
            "msg": {
                "description": null,
                "is_optional": true
            }
        },
        "new_parameter": {},
        "old_type": "member_function",
        "new_type": "",
        "change_type": "api_removal",
        "IC": "FIC"
    },
    {
        "old_api": "gitdb.test.test_pack.TestPack.assertDictEqual",
        "new_api": "",
        "old_parameter": {
            "self": {
                "description": null,
                "is_optional": false
            },
            "d1": {
                "description": null,
                "is_optional": false
            },
            "d2": {
                "description": null,
                "is_optional": false
            },
            "msg": {
                "description": null,
                "is_optional": true
            }
        },
        "new_parameter": {},
        "old_type": "member_function",
        "new_type": "",
        "change_type": "api_removal",
        "IC": "FIC"
    },
    {
        "old_api": "gitdb.test.test_pack.TestPack.assertEqual",
        "new_api": "",
        "old_parameter": {
            "self": {
                "description": null,
                "is_optional": false
            },
            "first": {
                "description": null,
                "is_optional": false
            },
            "second": {
                "description": null,
                "is_optional": false
            },
            "msg": {
                "description": null,
                "is_optional": true
            }
        },
        "new_parameter": {},
        "old_type": "member_function",
        "new_type": "",
        "change_type": "api_removal",
        "IC": "FIC"
    },
    {
        "old_api": "gitdb.test.test_pack.TestPack.assertEquals",
        "new_api": "",
        "old_parameter": {
            "args": {
                "description": null,
                "is_optional": false
            },
            "kwargs": {
                "description": null,
                "is_optional": false
            }
        },
        "new_parameter": {},
        "old_type": "member_function",
        "new_type": "",
        "change_type": "api_removal",
        "IC": "FIC"
    },
    {
        "old_api": "gitdb.test.test_pack.TestPack.assertFalse",
        "new_api": "",
        "old_parameter": {
            "self": {
                "description": null,
                "is_optional": false
            },
            "expr": {
                "description": null,
                "is_optional": false
            },
            "msg": {
                "description": null,
                "is_optional": true
            }
        },
        "new_parameter": {},
        "old_type": "member_function",
        "new_type": "",
        "change_type": "api_removal",
        "IC": "FIC"
    },
    {
        "old_api": "gitdb.test.test_pack.TestPack.assertGreater",
        "new_api": "",
        "old_parameter": {
            "self": {
                "description": null,
                "is_optional": false
            },
            "a": {
                "description": null,
                "is_optional": false
            },
            "b": {
                "description": null,
                "is_optional": false
            },
            "msg": {
                "description": null,
                "is_optional": true
            }
        },
        "new_parameter": {},
        "old_type": "member_function",
        "new_type": "",
        "change_type": "api_removal",
        "IC": "FIC"
    },
    {
        "old_api": "gitdb.test.test_pack.TestPack.assertGreaterEqual",
        "new_api": "",
        "old_parameter": {
            "self": {
                "description": null,
                "is_optional": false
            },
            "a": {
                "description": null,
                "is_optional": false
            },
            "b": {
                "description": null,
                "is_optional": false
            },
            "msg": {
                "description": null,
                "is_optional": true
            }
        },
        "new_parameter": {},
        "old_type": "member_function",
        "new_type": "",
        "change_type": "api_removal",
        "IC": "FIC"
    },
    {
        "old_api": "gitdb.test.test_pack.TestPack.assertIn",
        "new_api": "",
        "old_parameter": {
            "self": {
                "description": null,
                "is_optional": false
            },
            "member": {
                "description": null,
                "is_optional": false
            },
            "container": {
                "description": null,
                "is_optional": false
            },
            "msg": {
                "description": null,
                "is_optional": true
            }
        },
        "new_parameter": {},
        "old_type": "member_function",
        "new_type": "",
        "change_type": "api_removal",
        "IC": "FIC"
    },
    {
        "old_api": "gitdb.test.test_pack.TestPack.assertIs",
        "new_api": "",
        "old_parameter": {
            "self": {
                "description": null,
                "is_optional": false
            },
            "expr1": {
                "description": null,
                "is_optional": false
            },
            "expr2": {
                "description": null,
                "is_optional": false
            },
            "msg": {
                "description": null,
                "is_optional": true
            }
        },
        "new_parameter": {},
        "old_type": "member_function",
        "new_type": "",
        "change_type": "api_removal",
        "IC": "FIC"
    },
    {
        "old_api": "gitdb.test.test_pack.TestPack.assertIsInstance",
        "new_api": "",
        "old_parameter": {
            "self": {
                "description": null,
                "is_optional": false
            },
            "obj": {
                "description": null,
                "is_optional": false
            },
            "cls": {
                "description": null,
                "is_optional": false
            },
            "msg": {
                "description": null,
                "is_optional": true
            }
        },
        "new_parameter": {},
        "old_type": "member_function",
        "new_type": "",
        "change_type": "api_removal",
        "IC": "FIC"
    },
    {
        "old_api": "gitdb.test.test_pack.TestPack.assertIsNone",
        "new_api": "",
        "old_parameter": {
            "self": {
                "description": null,
                "is_optional": false
            },
            "obj": {
                "description": null,
                "is_optional": false
            },
            "msg": {
                "description": null,
                "is_optional": true
            }
        },
        "new_parameter": {},
        "old_type": "member_function",
        "new_type": "",
        "change_type": "api_removal",
        "IC": "FIC"
    },
    {
        "old_api": "gitdb.test.test_pack.TestPack.assertIsNot",
        "new_api": "",
        "old_parameter": {
            "self": {
                "description": null,
                "is_optional": false
            },
            "expr1": {
                "description": null,
                "is_optional": false
            },
            "expr2": {
                "description": null,
                "is_optional": false
            },
            "msg": {
                "description": null,
                "is_optional": true
            }
        },
        "new_parameter": {},
        "old_type": "member_function",
        "new_type": "",
        "change_type": "api_removal",
        "IC": "FIC"
    },
    {
        "old_api": "gitdb.test.test_pack.TestPack.assertIsNotNone",
        "new_api": "",
        "old_parameter": {
            "self": {
                "description": null,
                "is_optional": false
            },
            "obj": {
                "description": null,
                "is_optional": false
            },
            "msg": {
                "description": null,
                "is_optional": true
            }
        },
        "new_parameter": {},
        "old_type": "member_function",
        "new_type": "",
        "change_type": "api_removal",
        "IC": "FIC"
    },
    {
        "old_api": "gitdb.test.test_pack.TestPack.assertLess",
        "new_api": "",
        "old_parameter": {
            "self": {
                "description": null,
                "is_optional": false
            },
            "a": {
                "description": null,
                "is_optional": false
            },
            "b": {
                "description": null,
                "is_optional": false
            },
            "msg": {
                "description": null,
                "is_optional": true
            }
        },
        "new_parameter": {},
        "old_type": "member_function",
        "new_type": "",
        "change_type": "api_removal",
        "IC": "FIC"
    },
    {
        "old_api": "gitdb.test.test_pack.TestPack.assertLessEqual",
        "new_api": "",
        "old_parameter": {
            "self": {
                "description": null,
                "is_optional": false
            },
            "a": {
                "description": null,
                "is_optional": false
            },
            "b": {
                "description": null,
                "is_optional": false
            },
            "msg": {
                "description": null,
                "is_optional": true
            }
        },
        "new_parameter": {},
        "old_type": "member_function",
        "new_type": "",
        "change_type": "api_removal",
        "IC": "FIC"
    },
    {
        "old_api": "gitdb.test.test_pack.TestPack.assertListEqual",
        "new_api": "",
        "old_parameter": {
            "self": {
                "description": null,
                "is_optional": false
            },
            "list1": {
                "description": null,
                "is_optional": false
            },
            "list2": {
                "description": null,
                "is_optional": false
            },
            "msg": {
                "description": null,
                "is_optional": true
            }
        },
        "new_parameter": {},
        "old_type": "member_function",
        "new_type": "",
        "change_type": "api_removal",
        "IC": "FIC"
    },
    {
        "old_api": "gitdb.test.test_pack.TestPack.assertLogs",
        "new_api": "",
        "old_parameter": {
            "self": {
                "description": null,
                "is_optional": false
            },
            "logger": {
                "description": null,
                "is_optional": true
            },
            "level": {
                "description": null,
                "is_optional": true
            }
        },
        "new_parameter": {},
        "old_type": "member_function",
        "new_type": "",
        "change_type": "api_removal",
        "IC": "FIC"
    },
    {
        "old_api": "gitdb.test.test_pack.TestPack.assertMultiLineEqual",
        "new_api": "",
        "old_parameter": {
            "self": {
                "description": null,
                "is_optional": false
            },
            "first": {
                "description": null,
                "is_optional": false
            },
            "second": {
                "description": null,
                "is_optional": false
            },
            "msg": {
                "description": null,
                "is_optional": true
            }
        },
        "new_parameter": {},
        "old_type": "member_function",
        "new_type": "",
        "change_type": "api_removal",
        "IC": "FIC"
    },
    {
        "old_api": "gitdb.test.test_pack.TestPack.assertNotAlmostEqual",
        "new_api": "",
        "old_parameter": {
            "self": {
                "description": null,
                "is_optional": false
            },
            "first": {
                "description": null,
                "is_optional": false
            },
            "second": {
                "description": null,
                "is_optional": false
            },
            "places": {
                "description": null,
                "is_optional": true
            },
            "msg": {
                "description": null,
                "is_optional": true
            },
            "delta": {
                "description": null,
                "is_optional": true
            }
        },
        "new_parameter": {},
        "old_type": "member_function",
        "new_type": "",
        "change_type": "api_removal",
        "IC": "FIC"
    },
    {
        "old_api": "gitdb.test.test_pack.TestPack.assertNotAlmostEquals",
        "new_api": "",
        "old_parameter": {
            "args": {
                "description": null,
                "is_optional": false
            },
            "kwargs": {
                "description": null,
                "is_optional": false
            }
        },
        "new_parameter": {},
        "old_type": "member_function",
        "new_type": "",
        "change_type": "api_removal",
        "IC": "FIC"
    },
    {
        "old_api": "gitdb.test.test_pack.TestPack.assertNotEqual",
        "new_api": "",
        "old_parameter": {
            "self": {
                "description": null,
                "is_optional": false
            },
            "first": {
                "description": null,
                "is_optional": false
            },
            "second": {
                "description": null,
                "is_optional": false
            },
            "msg": {
                "description": null,
                "is_optional": true
            }
        },
        "new_parameter": {},
        "old_type": "member_function",
        "new_type": "",
        "change_type": "api_removal",
        "IC": "FIC"
    },
    {
        "old_api": "gitdb.test.test_pack.TestPack.assertNotEquals",
        "new_api": "",
        "old_parameter": {
            "args": {
                "description": null,
                "is_optional": false
            },
            "kwargs": {
                "description": null,
                "is_optional": false
            }
        },
        "new_parameter": {},
        "old_type": "member_function",
        "new_type": "",
        "change_type": "api_removal",
        "IC": "FIC"
    },
    {
        "old_api": "gitdb.test.test_pack.TestPack.assertNotIn",
        "new_api": "",
        "old_parameter": {
            "self": {
                "description": null,
                "is_optional": false
            },
            "member": {
                "description": null,
                "is_optional": false
            },
            "container": {
                "description": null,
                "is_optional": false
            },
            "msg": {
                "description": null,
                "is_optional": true
            }
        },
        "new_parameter": {},
        "old_type": "member_function",
        "new_type": "",
        "change_type": "api_removal",
        "IC": "FIC"
    },
    {
        "old_api": "gitdb.test.test_pack.TestPack.assertNotIsInstance",
        "new_api": "",
        "old_parameter": {
            "self": {
                "description": null,
                "is_optional": false
            },
            "obj": {
                "description": null,
                "is_optional": false
            },
            "cls": {
                "description": null,
                "is_optional": false
            },
            "msg": {
                "description": null,
                "is_optional": true
            }
        },
        "new_parameter": {},
        "old_type": "member_function",
        "new_type": "",
        "change_type": "api_removal",
        "IC": "FIC"
    },
    {
        "old_api": "gitdb.test.test_pack.TestPack.assertNotRegex",
        "new_api": "",
        "old_parameter": {
            "self": {
                "description": null,
                "is_optional": false
            },
            "text": {
                "description": null,
                "is_optional": false
            },
            "unexpected_regex": {
                "description": null,
                "is_optional": false
            },
            "msg": {
                "description": null,
                "is_optional": true
            }
        },
        "new_parameter": {},
        "old_type": "member_function",
        "new_type": "",
        "change_type": "api_removal",
        "IC": "FIC"
    },
    {
        "old_api": "gitdb.test.test_pack.TestPack.assertNotRegexpMatches",
        "new_api": "",
        "old_parameter": {
            "args": {
                "description": null,
                "is_optional": false
            },
            "kwargs": {
                "description": null,
                "is_optional": false
            }
        },
        "new_parameter": {},
        "old_type": "member_function",
        "new_type": "",
        "change_type": "api_removal",
        "IC": "FIC"
    },
    {
        "old_api": "gitdb.test.test_pack.TestPack.assertRaises",
        "new_api": "",
        "old_parameter": {
            "self": {
                "description": null,
                "is_optional": false
            },
            "expected_exception": {
                "description": null,
                "is_optional": false
            },
            "args": {
                "description": null,
                "is_optional": false
            },
            "kwargs": {
                "description": null,
                "is_optional": false
            }
        },
        "new_parameter": {},
        "old_type": "member_function",
        "new_type": "",
        "change_type": "api_removal",
        "IC": "FIC"
    },
    {
        "old_api": "gitdb.test.test_pack.TestPack.assertRaisesRegex",
        "new_api": "",
        "old_parameter": {
            "self": {
                "description": null,
                "is_optional": false
            },
            "expected_exception": {
                "description": null,
                "is_optional": false
            },
            "expected_regex": {
                "description": null,
                "is_optional": false
            },
            "args": {
                "description": null,
                "is_optional": false
            },
            "kwargs": {
                "description": null,
                "is_optional": false
            }
        },
        "new_parameter": {},
        "old_type": "member_function",
        "new_type": "",
        "change_type": "api_removal",
        "IC": "FIC"
    },
    {
        "old_api": "gitdb.test.test_pack.TestPack.assertRaisesRegexp",
        "new_api": "",
        "old_parameter": {
            "args": {
                "description": null,
                "is_optional": false
            },
            "kwargs": {
                "description": null,
                "is_optional": false
            }
        },
        "new_parameter": {},
        "old_type": "member_function",
        "new_type": "",
        "change_type": "api_removal",
        "IC": "FIC"
    },
    {
        "old_api": "gitdb.test.test_pack.TestPack.assertRegex",
        "new_api": "",
        "old_parameter": {
            "self": {
                "description": null,
                "is_optional": false
            },
            "text": {
                "description": null,
                "is_optional": false
            },
            "expected_regex": {
                "description": null,
                "is_optional": false
            },
            "msg": {
                "description": null,
                "is_optional": true
            }
        },
        "new_parameter": {},
        "old_type": "member_function",
        "new_type": "",
        "change_type": "api_removal",
        "IC": "FIC"
    },
    {
        "old_api": "gitdb.test.test_pack.TestPack.assertRegexpMatches",
        "new_api": "",
        "old_parameter": {
            "args": {
                "description": null,
                "is_optional": false
            },
            "kwargs": {
                "description": null,
                "is_optional": false
            }
        },
        "new_parameter": {},
        "old_type": "member_function",
        "new_type": "",
        "change_type": "api_removal",
        "IC": "FIC"
    },
    {
        "old_api": "gitdb.test.test_pack.TestPack.assertSequenceEqual",
        "new_api": "",
        "old_parameter": {
            "self": {
                "description": null,
                "is_optional": false
            },
            "seq1": {
                "description": null,
                "is_optional": false
            },
            "seq2": {
                "description": null,
                "is_optional": false
            },
            "msg": {
                "description": null,
                "is_optional": true
            },
            "seq_type": {
                "description": null,
                "is_optional": true
            }
        },
        "new_parameter": {},
        "old_type": "member_function",
        "new_type": "",
        "change_type": "api_removal",
        "IC": "FIC"
    },
    {
        "old_api": "gitdb.test.test_pack.TestPack.assertSetEqual",
        "new_api": "",
        "old_parameter": {
            "self": {
                "description": null,
                "is_optional": false
            },
            "set1": {
                "description": null,
                "is_optional": false
            },
            "set2": {
                "description": null,
                "is_optional": false
            },
            "msg": {
                "description": null,
                "is_optional": true
            }
        },
        "new_parameter": {},
        "old_type": "member_function",
        "new_type": "",
        "change_type": "api_removal",
        "IC": "FIC"
    },
    {
        "old_api": "gitdb.test.test_pack.TestPack.assertTrue",
        "new_api": "",
        "old_parameter": {
            "self": {
                "description": null,
                "is_optional": false
            },
            "expr": {
                "description": null,
                "is_optional": false
            },
            "msg": {
                "description": null,
                "is_optional": true
            }
        },
        "new_parameter": {},
        "old_type": "member_function",
        "new_type": "",
        "change_type": "api_removal",
        "IC": "FIC"
    },
    {
        "old_api": "gitdb.test.test_pack.TestPack.assertTupleEqual",
        "new_api": "",
        "old_parameter": {
            "self": {
                "description": null,
                "is_optional": false
            },
            "tuple1": {
                "description": null,
                "is_optional": false
            },
            "tuple2": {
                "description": null,
                "is_optional": false
            },
            "msg": {
                "description": null,
                "is_optional": true
            }
        },
        "new_parameter": {},
        "old_type": "member_function",
        "new_type": "",
        "change_type": "api_removal",
        "IC": "FIC"
    },
    {
        "old_api": "gitdb.test.test_pack.TestPack.assertWarns",
        "new_api": "",
        "old_parameter": {
            "self": {
                "description": null,
                "is_optional": false
            },
            "expected_warning": {
                "description": null,
                "is_optional": false
            },
            "args": {
                "description": null,
                "is_optional": false
            },
            "kwargs": {
                "description": null,
                "is_optional": false
            }
        },
        "new_parameter": {},
        "old_type": "member_function",
        "new_type": "",
        "change_type": "api_removal",
        "IC": "FIC"
    },
    {
        "old_api": "gitdb.test.test_pack.TestPack.assertWarnsRegex",
        "new_api": "",
        "old_parameter": {
            "self": {
                "description": null,
                "is_optional": false
            },
            "expected_warning": {
                "description": null,
                "is_optional": false
            },
            "expected_regex": {
                "description": null,
                "is_optional": false
            },
            "args": {
                "description": null,
                "is_optional": false
            },
            "kwargs": {
                "description": null,
                "is_optional": false
            }
        },
        "new_parameter": {},
        "old_type": "member_function",
        "new_type": "",
        "change_type": "api_removal",
        "IC": "FIC"
    },
    {
        "old_api": "gitdb.test.test_pack.TestPack.assert_",
        "new_api": "",
        "old_parameter": {
            "args": {
                "description": null,
                "is_optional": false
            },
            "kwargs": {
                "description": null,
                "is_optional": false
            }
        },
        "new_parameter": {},
        "old_type": "member_function",
        "new_type": "",
        "change_type": "api_removal",
        "IC": "FIC"
    },
    {
        "old_api": "gitdb.test.test_pack.TestPack.countTestCases",
        "new_api": "",
        "old_parameter": {
            "self": {
                "description": null,
                "is_optional": false
            }
        },
        "new_parameter": {},
        "old_type": "member_function",
        "new_type": "",
        "change_type": "api_removal",
        "IC": "FIC"
    },
    {
        "old_api": "gitdb.test.test_pack.TestPack.debug",
        "new_api": "",
        "old_parameter": {
            "self": {
                "description": null,
                "is_optional": false
            }
        },
        "new_parameter": {},
        "old_type": "member_function",
        "new_type": "",
        "change_type": "api_removal",
        "IC": "FIC"
    },
    {
        "old_api": "gitdb.test.test_pack.TestPack.defaultTestResult",
        "new_api": "",
        "old_parameter": {
            "self": {
                "description": null,
                "is_optional": false
            }
        },
        "new_parameter": {},
        "old_type": "member_function",
        "new_type": "",
        "change_type": "api_removal",
        "IC": "FIC"
    },
    {
        "old_api": "gitdb.test.test_pack.TestPack.doCleanups",
        "new_api": "",
        "old_parameter": {
            "self": {
                "description": null,
                "is_optional": false
            }
        },
        "new_parameter": {},
        "old_type": "member_function",
        "new_type": "",
        "change_type": "api_removal",
        "IC": "FIC"
    },
    {
        "old_api": "gitdb.test.test_pack.TestPack.fail",
        "new_api": "",
        "old_parameter": {
            "self": {
                "description": null,
                "is_optional": false
            },
            "msg": {
                "description": null,
                "is_optional": true
            }
        },
        "new_parameter": {},
        "old_type": "member_function",
        "new_type": "",
        "change_type": "api_removal",
        "IC": "FIC"
    },
    {
        "old_api": "gitdb.test.test_pack.TestPack.failIf",
        "new_api": "",
        "old_parameter": {
            "args": {
                "description": null,
                "is_optional": false
            },
            "kwargs": {
                "description": null,
                "is_optional": false
            }
        },
        "new_parameter": {},
        "old_type": "member_function",
        "new_type": "",
        "change_type": "api_removal",
        "IC": "FIC"
    },
    {
        "old_api": "gitdb.test.test_pack.TestPack.failIfAlmostEqual",
        "new_api": "",
        "old_parameter": {
            "args": {
                "description": null,
                "is_optional": false
            },
            "kwargs": {
                "description": null,
                "is_optional": false
            }
        },
        "new_parameter": {},
        "old_type": "member_function",
        "new_type": "",
        "change_type": "api_removal",
        "IC": "FIC"
    },
    {
        "old_api": "gitdb.test.test_pack.TestPack.failIfEqual",
        "new_api": "",
        "old_parameter": {
            "args": {
                "description": null,
                "is_optional": false
            },
            "kwargs": {
                "description": null,
                "is_optional": false
            }
        },
        "new_parameter": {},
        "old_type": "member_function",
        "new_type": "",
        "change_type": "api_removal",
        "IC": "FIC"
    },
    {
        "old_api": "gitdb.test.test_pack.TestPack.failUnless",
        "new_api": "",
        "old_parameter": {
            "args": {
                "description": null,
                "is_optional": false
            },
            "kwargs": {
                "description": null,
                "is_optional": false
            }
        },
        "new_parameter": {},
        "old_type": "member_function",
        "new_type": "",
        "change_type": "api_removal",
        "IC": "FIC"
    },
    {
        "old_api": "gitdb.test.test_pack.TestPack.failUnlessAlmostEqual",
        "new_api": "",
        "old_parameter": {
            "args": {
                "description": null,
                "is_optional": false
            },
            "kwargs": {
                "description": null,
                "is_optional": false
            }
        },
        "new_parameter": {},
        "old_type": "member_function",
        "new_type": "",
        "change_type": "api_removal",
        "IC": "FIC"
    },
    {
        "old_api": "gitdb.test.test_pack.TestPack.failUnlessEqual",
        "new_api": "",
        "old_parameter": {
            "args": {
                "description": null,
                "is_optional": false
            },
            "kwargs": {
                "description": null,
                "is_optional": false
            }
        },
        "new_parameter": {},
        "old_type": "member_function",
        "new_type": "",
        "change_type": "api_removal",
        "IC": "FIC"
    },
    {
        "old_api": "gitdb.test.test_pack.TestPack.failUnlessRaises",
        "new_api": "",
        "old_parameter": {
            "args": {
                "description": null,
                "is_optional": false
            },
            "kwargs": {
                "description": null,
                "is_optional": false
            }
        },
        "new_parameter": {},
        "old_type": "member_function",
        "new_type": "",
        "change_type": "api_removal",
        "IC": "FIC"
    },
    {
        "old_api": "gitdb.test.test_pack.TestPack.id",
        "new_api": "",
        "old_parameter": {
            "self": {
                "description": null,
                "is_optional": false
            }
        },
        "new_parameter": {},
        "old_type": "member_function",
        "new_type": "",
        "change_type": "api_removal",
        "IC": "FIC"
    },
    {
        "old_api": "gitdb.test.test_pack.TestPack.run",
        "new_api": "",
        "old_parameter": {
            "self": {
                "description": null,
                "is_optional": false
            },
            "result": {
                "description": null,
                "is_optional": true
            }
        },
        "new_parameter": {},
        "old_type": "member_function",
        "new_type": "",
        "change_type": "api_removal",
        "IC": "FIC"
    },
    {
        "old_api": "gitdb.test.test_pack.TestPack.setUp",
        "new_api": "",
        "old_parameter": {
            "self": {
                "description": null,
                "is_optional": false
            }
        },
        "new_parameter": {},
        "old_type": "member_function",
        "new_type": "",
        "change_type": "api_removal",
        "IC": "FIC"
    },
    {
        "old_api": "gitdb.test.test_pack.TestPack.shortDescription",
        "new_api": "",
        "old_parameter": {
            "self": {
                "description": null,
                "is_optional": false
            }
        },
        "new_parameter": {},
        "old_type": "member_function",
        "new_type": "",
        "change_type": "api_removal",
        "IC": "FIC"
    },
    {
        "old_api": "gitdb.test.test_pack.TestPack.skipTest",
        "new_api": "",
        "old_parameter": {
            "self": {
                "description": null,
                "is_optional": false
            },
            "reason": {
                "description": null,
                "is_optional": false
            }
        },
        "new_parameter": {},
        "old_type": "member_function",
        "new_type": "",
        "change_type": "api_removal",
        "IC": "FIC"
    },
    {
        "old_api": "gitdb.test.test_pack.TestPack.subTest",
        "new_api": "",
        "old_parameter": {
            "self": {
                "description": null,
                "is_optional": false
            },
            "msg": {
                "description": null,
                "is_optional": true
            },
            "params": {
                "description": null,
                "is_optional": false
            }
        },
        "new_parameter": {},
        "old_type": "member_function",
        "new_type": "",
        "change_type": "api_removal",
        "IC": "FIC"
    },
    {
        "old_api": "gitdb.test.test_pack.TestPack.tearDown",
        "new_api": "",
        "old_parameter": {
            "self": {
                "description": null,
                "is_optional": false
            }
        },
        "new_parameter": {},
        "old_type": "member_function",
        "new_type": "",
        "change_type": "api_removal",
        "IC": "FIC"
    },
    {
        "old_api": "gitdb.test.test_pack.TestPack.test_pack",
        "new_api": "",
        "old_parameter": {
            "self": {
                "description": null,
                "is_optional": false
            }
        },
        "new_parameter": {},
        "old_type": "member_function",
        "new_type": "",
        "change_type": "api_removal",
        "IC": "FIC"
    },
    {
        "old_api": "gitdb.test.test_pack.TestPack.test_pack_64",
        "new_api": "",
        "old_parameter": {
            "self": {
                "description": null,
                "is_optional": false
            }
        },
        "new_parameter": {},
        "old_type": "member_function",
        "new_type": "",
        "change_type": "api_removal",
        "IC": "FIC"
    },
    {
        "old_api": "gitdb.test.test_pack.TestPack.test_pack_entity",
        "new_api": "",
        "old_parameter": {
            "self": {
                "description": null,
                "is_optional": false
            }
        },
        "new_parameter": {},
        "old_type": "member_function",
        "new_type": "",
        "change_type": "api_removal",
        "IC": "FIC"
    },
    {
        "old_api": "gitdb.test.test_pack.TestPack.test_pack_index",
        "new_api": "",
        "old_parameter": {
            "self": {
                "description": null,
                "is_optional": false
            }
        },
        "new_parameter": {},
        "old_type": "member_function",
        "new_type": "",
        "change_type": "api_removal",
        "IC": "FIC"
    },
    {
        "old_api": "gitdb.test.test_pack.TestPack",
        "new_api": "",
        "old_parameter": {},
        "new_parameter": {},
        "old_type": "class",
        "new_type": "",
        "change_type": "api_removal",
        "IC": "FIC"
    },
    {
        "old_api": "gitdb.test.test_pack.bin_sha_from_filename",
        "new_api": "",
        "old_parameter": {
            "filename": {
                "description": null,
                "is_optional": false
            }
        },
        "new_parameter": {},
        "old_type": "function",
        "new_type": "",
        "change_type": "api_removal",
        "IC": "FIC"
    },
    {
        "old_api": "gitdb.utils.compat.buffer",
        "new_api": "",
        "old_parameter": {
            "obj": {
                "description": null,
                "is_optional": false
            },
            "offset": {
                "description": null,
                "is_optional": false
            },
            "size": {
                "description": null,
                "is_optional": true
            }
        },
        "new_parameter": {},
        "old_type": "function",
        "new_type": "",
        "change_type": "api_removal",
        "IC": "FIC"
    },
    {
        "old_api": "gitdb.utils.compat.to_bytes",
        "new_api": "",
        "old_parameter": {
            "i": {
                "description": null,
                "is_optional": false
            }
        },
        "new_parameter": {},
        "old_type": "function",
        "new_type": "",
        "change_type": "api_removal",
        "IC": "FIC"
    },
    {
        "old_api": "gitdb.utils.encoding.string_types",
        "new_api": "",
        "old_parameter": {},
        "new_parameter": {},
        "old_type": "module_field",
        "new_type": "",
        "change_type": "api_removal",
        "IC": "FIC"
    },
    {
        "old_api": "gitdb.db.pack.xrange",
        "new_api": "",
        "old_parameter": {},
        "new_parameter": {},
        "old_type": "dir api",
        "new_type": "",
        "change_type": "api_removal",
        "IC": "FIC"
    },
    {
        "old_api": "gitdb.fun.buffer",
        "new_api": "",
        "old_parameter": {},
        "new_parameter": {},
        "old_type": "dir api",
        "new_type": "",
        "change_type": "api_removal",
        "IC": "FIC"
    },
    {
        "old_api": "gitdb.fun.izip",
        "new_api": "",
        "old_parameter": {},
        "new_parameter": {},
        "old_type": "dir api",
        "new_type": "",
        "change_type": "api_removal",
        "IC": "FIC"
    },
    {
        "old_api": "gitdb.fun.xrange",
        "new_api": "",
        "old_parameter": {},
        "new_parameter": {},
        "old_type": "dir api",
        "new_type": "",
        "change_type": "api_removal",
        "IC": "FIC"
    },
    {
        "old_api": "gitdb.pack.buffer",
        "new_api": "",
        "old_parameter": {},
        "new_parameter": {},
        "old_type": "dir api",
        "new_type": "",
        "change_type": "api_removal",
        "IC": "FIC"
    },
    {
        "old_api": "gitdb.pack.izip",
        "new_api": "",
        "old_parameter": {},
        "new_parameter": {},
        "old_type": "dir api",
        "new_type": "",
        "change_type": "api_removal",
        "IC": "FIC"
    },
    {
        "old_api": "gitdb.pack.to_bytes",
        "new_api": "",
        "old_parameter": {},
        "new_parameter": {},
        "old_type": "dir api",
        "new_type": "",
        "change_type": "api_removal",
        "IC": "FIC"
    },
    {
        "old_api": "gitdb.pack.xrange",
        "new_api": "",
        "old_parameter": {},
        "new_parameter": {},
        "old_type": "dir api",
        "new_type": "",
        "change_type": "api_removal",
        "IC": "FIC"
    },
    {
        "old_api": "gitdb.stream.buffer",
        "new_api": "",
        "old_parameter": {},
        "new_parameter": {},
        "old_type": "dir api",
        "new_type": "",
        "change_type": "api_removal",
        "IC": "FIC"
    },
    {
        "old_api": "gitdb.test.lib.xrange",
        "new_api": "",
        "old_parameter": {},
        "new_parameter": {},
        "old_type": "dir api",
        "new_type": "",
        "change_type": "api_removal",
        "IC": "FIC"
    },
    {
        "old_api": "gitdb.test.test_pack.DeltaApplyReader",
        "new_api": "",
        "old_parameter": {},
        "new_parameter": {},
        "old_type": "dir api",
        "new_type": "",
        "change_type": "api_removal",
        "IC": "FIC"
    },
    {
        "old_api": "gitdb.test.test_pack.OInfo",
        "new_api": "",
        "old_parameter": {},
        "new_parameter": {},
        "old_type": "dir api",
        "new_type": "",
        "change_type": "api_removal",
        "IC": "FIC"
    },
    {
        "old_api": "gitdb.test.test_pack.OStream",
        "new_api": "",
        "old_parameter": {},
        "new_parameter": {},
        "old_type": "dir api",
        "new_type": "",
        "change_type": "api_removal",
        "IC": "FIC"
    },
    {
        "old_api": "gitdb.test.test_pack.PackEntity",
        "new_api": "",
        "old_parameter": {},
        "new_parameter": {},
        "old_type": "dir api",
        "new_type": "",
        "change_type": "api_removal",
        "IC": "FIC"
    },
    {
        "old_api": "gitdb.test.test_pack.PackFile",
        "new_api": "",
        "old_parameter": {},
        "new_parameter": {},
        "old_type": "dir api",
        "new_type": "",
        "change_type": "api_removal",
        "IC": "FIC"
    },
    {
        "old_api": "gitdb.test.test_pack.PackIndexFile",
        "new_api": "",
        "old_parameter": {},
        "new_parameter": {},
        "old_type": "dir api",
        "new_type": "",
        "change_type": "api_removal",
        "IC": "FIC"
    },
    {
        "old_api": "gitdb.test.test_pack.SkipTest",
        "new_api": "",
        "old_parameter": {},
        "new_parameter": {},
        "old_type": "dir api",
        "new_type": "",
        "change_type": "api_removal",
        "IC": "FIC"
    },
    {
        "old_api": "gitdb.test.test_pack.TestBase",
        "new_api": "",
        "old_parameter": {},
        "new_parameter": {},
        "old_type": "dir api",
        "new_type": "",
        "change_type": "api_removal",
        "IC": "FIC"
    },
    {
        "old_api": "gitdb.test.test_pack.UnsupportedOperation",
        "new_api": "",
        "old_parameter": {},
        "new_parameter": {},
        "old_type": "dir api",
        "new_type": "",
        "change_type": "api_removal",
        "IC": "FIC"
    },
    {
        "old_api": "gitdb.test.test_pack.delta_types",
        "new_api": "",
        "old_parameter": {},
        "new_parameter": {},
        "old_type": "dir api",
        "new_type": "",
        "change_type": "api_removal",
        "IC": "FIC"
    },
    {
        "old_api": "gitdb.test.test_pack.fixture_path",
        "new_api": "",
        "old_parameter": {},
        "new_parameter": {},
        "old_type": "dir api",
        "new_type": "",
        "change_type": "api_removal",
        "IC": "FIC"
    },
    {
        "old_api": "gitdb.test.test_pack.izip",
        "new_api": "",
        "old_parameter": {},
        "new_parameter": {},
        "old_type": "dir api",
        "new_type": "",
        "change_type": "api_removal",
        "IC": "FIC"
    },
    {
        "old_api": "gitdb.test.test_pack.os",
        "new_api": "",
        "old_parameter": {},
        "new_parameter": {},
        "old_type": "dir api",
        "new_type": "",
        "change_type": "api_removal",
        "IC": "FIC"
    },
    {
        "old_api": "gitdb.test.test_pack.tempfile",
        "new_api": "",
        "old_parameter": {},
        "new_parameter": {},
        "old_type": "dir api",
        "new_type": "",
        "change_type": "api_removal",
        "IC": "FIC"
    },
    {
        "old_api": "gitdb.test.test_pack.to_bin_sha",
        "new_api": "",
        "old_parameter": {},
        "new_parameter": {},
        "old_type": "dir api",
        "new_type": "",
        "change_type": "api_removal",
        "IC": "FIC"
    },
    {
        "old_api": "gitdb.test.test_pack.with_rw_directory",
        "new_api": "",
        "old_parameter": {},
        "new_parameter": {},
        "old_type": "dir api",
        "new_type": "",
        "change_type": "api_removal",
        "IC": "FIC"
    },
    {
        "old_api": "gitdb.test.test_pack.xrange",
        "new_api": "",
        "old_parameter": {},
        "new_parameter": {},
        "old_type": "dir api",
        "new_type": "",
        "change_type": "api_removal",
        "IC": "FIC"
    },
    {
        "old_api": "gitdb.utils.compat",
        "new_api": "",
        "old_parameter": {},
        "new_parameter": {},
        "old_type": "dir api",
        "new_type": "",
        "change_type": "api_removal",
        "IC": "FIC"
    },
    {
        "old_api": "gitdb.utils.compat.MAXSIZE",
        "new_api": "",
        "old_parameter": {},
        "new_parameter": {},
        "old_type": "dir api",
        "new_type": "",
        "change_type": "api_removal",
        "IC": "FIC"
    },
    {
        "old_api": "gitdb.utils.compat.PY3",
        "new_api": "",
        "old_parameter": {},
        "new_parameter": {},
        "old_type": "dir api",
        "new_type": "",
        "change_type": "api_removal",
        "IC": "FIC"
    },
    {
        "old_api": "gitdb.utils.compat.izip",
        "new_api": "",
        "old_parameter": {},
        "new_parameter": {},
        "old_type": "dir api",
        "new_type": "",
        "change_type": "api_removal",
        "IC": "FIC"
    },
    {
        "old_api": "gitdb.utils.compat.memoryview",
        "new_api": "",
        "old_parameter": {},
        "new_parameter": {},
        "old_type": "dir api",
        "new_type": "",
        "change_type": "api_removal",
        "IC": "FIC"
    },
    {
        "old_api": "gitdb.utils.compat.sys",
        "new_api": "",
        "old_parameter": {},
        "new_parameter": {},
        "old_type": "dir api",
        "new_type": "",
        "change_type": "api_removal",
        "IC": "FIC"
    },
    {
        "old_api": "gitdb.utils.compat.xrange",
        "new_api": "",
        "old_parameter": {},
        "new_parameter": {},
        "old_type": "dir api",
        "new_type": "",
        "change_type": "api_removal",
        "IC": "FIC"
    },
    {
        "old_api": "gitdb.utils.encoding.compat",
        "new_api": "",
        "old_parameter": {},
        "new_parameter": {},
        "old_type": "dir api",
        "new_type": "",
        "change_type": "api_removal",
        "IC": "FIC"
    },
    {
        "old_api": "gitdb.utils.encoding.text_type",
        "new_api": "",
        "old_parameter": {},
        "new_parameter": {},
        "old_type": "dir api",
        "new_type": "",
        "change_type": "api_removal",
        "IC": "FIC"
    },
    {
        "old_api": "",
        "new_api": "gitdb.db.loose.sys",
        "old_parameter": {},
        "new_parameter": {},
        "old_type": "",
        "new_type": "dir api",
        "change_type": "api_addition",
        "IC": "BIC"
    }
]