[
    {
        "old_api": "numexpr.necompiler.re_evaluate",
        "new_api": "numexpr.necompiler.re_evaluate",
        "old_parameter": {
            "local_dict": {
                "description": null,
                "is_optional": true
            }
        },
        "new_parameter": {
            "local_dict": {
                "description": null,
                "is_optional": true
            },
            "_frame_depth": {
                "description": null,
                "is_optional": true
            }
        },
        "change_type": "optional_param_addition",
        "IC": "BIC",
        "change": "_frame_depth"
    },
    {
        "old_api": "numexpr.necompiler.getArguments",
        "new_api": "numexpr.necompiler.getArguments",
        "old_parameter": {
            "names": {
                "description": null,
                "is_optional": false
            },
            "local_dict": {
                "description": null,
                "is_optional": true
            },
            "global_dict": {
                "description": null,
                "is_optional": true
            }
        },
        "new_parameter": {
            "names": {
                "description": null,
                "is_optional": false
            },
            "local_dict": {
                "description": null,
                "is_optional": true
            },
            "global_dict": {
                "description": null,
                "is_optional": true
            },
            "_frame_depth": {
                "description": null,
                "is_optional": true
            }
        },
        "change_type": "optional_param_addition",
        "IC": "BIC",
        "change": "_frame_depth"
    },
    {
        "old_api": "numexpr.re_evaluate",
        "new_api": "numexpr.re_evaluate",
        "old_parameter": {
            "local_dict": {
                "description": null,
                "is_optional": true
            }
        },
        "new_parameter": {
            "local_dict": {
                "description": null,
                "is_optional": true
            },
            "_frame_depth": {
                "description": null,
                "is_optional": true
            }
        },
        "change_type": "optional_param_addition",
        "IC": "BIC",
        "change": "_frame_depth"
    },
    {
        "old_api": "numexpr.get_info",
        "new_api": "",
        "old_parameter": {
            "name": {
                "description": null,
                "is_optional": false
            }
        },
        "new_parameter": {},
        "old_type": "function",
        "new_type": "",
        "change_type": "api_removal",
        "IC": "FIC"
    },
    {
        "old_api": "numexpr.show_config",
        "new_api": "",
        "old_parameter": {},
        "new_parameter": {},
        "old_type": "function",
        "new_type": "",
        "change_type": "api_removal",
        "IC": "FIC"
    },
    {
        "old_api": "numexpr.__config__.extra_dll_dir",
        "new_api": "",
        "old_parameter": {},
        "new_parameter": {},
        "old_type": "module_field",
        "new_type": "",
        "change_type": "api_removal",
        "IC": "FIC"
    },
    {
        "old_api": "numexpr.__config__.get_info",
        "new_api": "",
        "old_parameter": {
            "name": {
                "description": null,
                "is_optional": false
            }
        },
        "new_parameter": {},
        "old_type": "function",
        "new_type": "",
        "change_type": "api_removal",
        "IC": "FIC"
    },
    {
        "old_api": "numexpr.__config__.show",
        "new_api": "",
        "old_parameter": {},
        "new_parameter": {},
        "old_type": "function",
        "new_type": "",
        "change_type": "api_removal",
        "IC": "FIC"
    },
    {
        "old_api": "numexpr.expressions.Expression.__init__",
        "new_api": "",
        "old_parameter": {
            "self": {
                "description": null,
                "is_optional": false
            }
        },
        "new_parameter": {},
        "old_type": "member_function",
        "new_type": "",
        "change_type": "api_removal",
        "IC": "FIC"
    },
    {
        "old_api": "numexpr.__config__",
        "new_api": "",
        "old_parameter": {},
        "new_parameter": {},
        "old_type": "dir api",
        "new_type": "",
        "change_type": "api_removal",
        "IC": "FIC"
    },
    {
        "old_api": "numexpr.__config__.__all__",
        "new_api": "",
        "old_parameter": {},
        "new_parameter": {},
        "old_type": "dir api",
        "new_type": "",
        "change_type": "api_removal",
        "IC": "FIC"
    },
    {
        "old_api": "numexpr.__config__.os",
        "new_api": "",
        "old_parameter": {},
        "new_parameter": {},
        "old_type": "dir api",
        "new_type": "",
        "change_type": "api_removal",
        "IC": "FIC"
    },
    {
        "old_api": "numexpr.__config__.sys",
        "new_api": "",
        "old_parameter": {},
        "new_parameter": {},
        "old_type": "dir api",
        "new_type": "",
        "change_type": "api_removal",
        "IC": "FIC"
    },
    {
        "old_api": "numexpr.expressions.LooseVersion",
        "new_api": "",
        "old_parameter": {},
        "new_parameter": {},
        "old_type": "dir api",
        "new_type": "",
        "change_type": "api_removal",
        "IC": "FIC"
    },
    {
        "old_api": "numexpr.expressions._np_version_forbids_neg_powint",
        "new_api": "",
        "old_parameter": {},
        "new_parameter": {},
        "old_type": "dir api",
        "new_type": "",
        "change_type": "api_removal",
        "IC": "FIC"
    },
    {
        "old_api": "numexpr.tests.test_numexpr.LooseVersion",
        "new_api": "",
        "old_parameter": {},
        "new_parameter": {},
        "old_type": "dir api",
        "new_type": "",
        "change_type": "api_removal",
        "IC": "FIC"
    },
    {
        "old_api": "numexpr.tests.test_numexpr.minimum_numpy_version",
        "new_api": "",
        "old_parameter": {},
        "new_parameter": {},
        "old_type": "dir api",
        "new_type": "",
        "change_type": "api_removal",
        "IC": "FIC"
    },
    {
        "old_api": "",
        "new_api": "numexpr.get_num_threads",
        "old_parameter": {},
        "new_parameter": {},
        "old_type": "",
        "new_type": "function",
        "change_type": "api_addition",
        "IC": "BIC"
    },
    {
        "old_api": "",
        "new_api": "numexpr.validate",
        "old_parameter": {},
        "new_parameter": {
            "ex": {
                "description": null,
                "is_optional": false
            },
            "local_dict": {
                "description": null,
                "is_optional": true
            },
            "global_dict": {
                "description": null,
                "is_optional": true
            },
            "out": {
                "description": null,
                "is_optional": true
            },
            "order": {
                "description": null,
                "is_optional": true
            },
            "casting": {
                "description": null,
                "is_optional": true
            },
            "_frame_depth": {
                "description": null,
                "is_optional": true
            },
            "kwargs": {
                "description": null,
                "is_optional": false
            }
        },
        "old_type": "",
        "new_type": "function",
        "change_type": "api_addition",
        "IC": "BIC"
    },
    {
        "old_api": "",
        "new_api": "numexpr.necompiler.Dict",
        "old_parameter": {},
        "new_parameter": {},
        "old_type": "",
        "new_type": "module_field",
        "change_type": "api_addition",
        "IC": "BIC"
    },
    {
        "old_api": "",
        "new_api": "numexpr.necompiler.Optional",
        "old_parameter": {},
        "new_parameter": {},
        "old_type": "",
        "new_type": "module_field",
        "change_type": "api_addition",
        "IC": "BIC"
    },
    {
        "old_api": "",
        "new_api": "numexpr.necompiler.validate",
        "old_parameter": {},
        "new_parameter": {
            "ex": {
                "description": null,
                "is_optional": false
            },
            "local_dict": {
                "description": null,
                "is_optional": true
            },
            "global_dict": {
                "description": null,
                "is_optional": true
            },
            "out": {
                "description": null,
                "is_optional": true
            },
            "order": {
                "description": null,
                "is_optional": true
            },
            "casting": {
                "description": null,
                "is_optional": true
            },
            "_frame_depth": {
                "description": null,
                "is_optional": true
            },
            "kwargs": {
                "description": null,
                "is_optional": false
            }
        },
        "old_type": "",
        "new_type": "function",
        "change_type": "api_addition",
        "IC": "BIC"
    },
    {
        "old_api": "",
        "new_api": "numexpr.utils.get_vml_num_threads",
        "old_parameter": {},
        "new_parameter": {},
        "old_type": "",
        "new_type": "function",
        "change_type": "api_addition",
        "IC": "BIC"
    },
    {
        "old_api": "",
        "new_api": "numexpr.version.numpy_build_version",
        "old_parameter": {},
        "new_parameter": {},
        "old_type": "",
        "new_type": "module_field",
        "change_type": "api_addition",
        "IC": "BIC"
    },
    {
        "old_api": "",
        "new_api": "numexpr.version.platform_machine",
        "old_parameter": {},
        "new_parameter": {},
        "old_type": "",
        "new_type": "module_field",
        "change_type": "api_addition",
        "IC": "BIC"
    },
    {
        "old_api": "",
        "new_api": "numexpr.__BLOCK_SIZE1__",
        "old_parameter": {},
        "new_parameter": {},
        "old_type": "",
        "new_type": "dir api",
        "change_type": "api_addition",
        "IC": "BIC"
    },
    {
        "old_api": "",
        "new_api": "numexpr.interpreter.__BLOCK_SIZE1__",
        "old_parameter": {},
        "new_parameter": {},
        "old_type": "",
        "new_type": "dir api",
        "change_type": "api_addition",
        "IC": "BIC"
    },
    {
        "old_api": "",
        "new_api": "numexpr.interpreter._get_num_threads",
        "old_parameter": {},
        "new_parameter": {},
        "old_type": "",
        "new_type": "dir api",
        "change_type": "api_addition",
        "IC": "BIC"
    },
    {
        "old_api": "",
        "new_api": "numexpr.interpreter.use_vml",
        "old_parameter": {},
        "new_parameter": {},
        "old_type": "",
        "new_type": "dir api",
        "change_type": "api_addition",
        "IC": "BIC"
    },
    {
        "old_api": "",
        "new_api": "numexpr.necompiler._forbidden_re",
        "old_parameter": {},
        "new_parameter": {},
        "old_type": "",
        "new_type": "dir api",
        "change_type": "api_addition",
        "IC": "BIC"
    },
    {
        "old_api": "",
        "new_api": "numexpr.necompiler.re",
        "old_parameter": {},
        "new_parameter": {},
        "old_type": "",
        "new_type": "dir api",
        "change_type": "api_addition",
        "IC": "BIC"
    },
    {
        "old_api": "",
        "new_api": "numexpr.tests.test_numexpr.ConstantNode",
        "old_parameter": {},
        "new_parameter": {},
        "old_type": "",
        "new_type": "dir api",
        "change_type": "api_addition",
        "IC": "BIC"
    },
    {
        "old_api": "",
        "new_api": "numexpr.tests.test_numexpr.numpy",
        "old_parameter": {},
        "new_parameter": {},
        "old_type": "",
        "new_type": "dir api",
        "change_type": "api_addition",
        "IC": "BIC"
    },
    {
        "old_api": "",
        "new_api": "numexpr.tests.test_numexpr.validate",
        "old_parameter": {},
        "new_parameter": {},
        "old_type": "",
        "new_type": "dir api",
        "change_type": "api_addition",
        "IC": "BIC"
    },
    {
        "old_api": "",
        "new_api": "numexpr.utils._get_num_threads",
        "old_parameter": {},
        "new_parameter": {},
        "old_type": "",
        "new_type": "dir api",
        "change_type": "api_addition",
        "IC": "BIC"
    },
    {
        "old_api": "",
        "new_api": "numexpr.utils.get_num_threads",
        "old_parameter": {},
        "new_parameter": {},
        "old_type": "",
        "new_type": "dir api",
        "change_type": "api_addition",
        "IC": "BIC"
    },
    {
        "old_api": "",
        "new_api": "numexpr.utils.version",
        "old_parameter": {},
        "new_parameter": {},
        "old_type": "",
        "new_type": "dir api",
        "change_type": "api_addition",
        "IC": "BIC"
    }
]