[
    {
        "old_api": "trollimage.colormap.Colormap.__add__",
        "new_api": "",
        "old_parameter": {
            "self": {
                "description": null,
                "is_optional": false
            },
            "other": {
                "description": null,
                "is_optional": false
            }
        },
        "new_parameter": {},
        "old_type": "member_function",
        "new_type": "",
        "change_type": "api_removal",
        "IC": "FIC"
    },
    {
        "old_api": "trollimage.colormap.Colormap.__init__",
        "new_api": "",
        "old_parameter": {
            "self": {
                "description": null,
                "is_optional": false
            },
            "tuples": {
                "description": null,
                "is_optional": false
            },
            "kwargs": {
                "description": null,
                "is_optional": false
            }
        },
        "new_parameter": {},
        "old_type": "member_function",
        "new_type": "",
        "change_type": "api_removal",
        "IC": "FIC"
    },
    {
        "old_api": "trollimage.colormap.Colormap.colorize",
        "new_api": "",
        "old_parameter": {
            "self": {
                "description": null,
                "is_optional": false
            },
            "data": {
                "description": null,
                "is_optional": false
            }
        },
        "new_parameter": {},
        "old_type": "member_function",
        "new_type": "",
        "change_type": "api_removal",
        "IC": "FIC"
    },
    {
        "old_api": "trollimage.colormap.Colormap.palettize",
        "new_api": "",
        "old_parameter": {
            "self": {
                "description": null,
                "is_optional": false
            },
            "data": {
                "description": null,
                "is_optional": false
            }
        },
        "new_parameter": {},
        "old_type": "member_function",
        "new_type": "",
        "change_type": "api_removal",
        "IC": "FIC"
    },
    {
        "old_api": "trollimage.colormap.Colormap.reverse",
        "new_api": "",
        "old_parameter": {
            "self": {
                "description": null,
                "is_optional": false
            }
        },
        "new_parameter": {},
        "old_type": "member_function",
        "new_type": "",
        "change_type": "api_removal",
        "IC": "FIC"
    },
    {
        "old_api": "trollimage.colormap.Colormap.set_range",
        "new_api": "",
        "old_parameter": {
            "self": {
                "description": null,
                "is_optional": false
            },
            "min_val": {
                "description": null,
                "is_optional": false
            },
            "max_val": {
                "description": null,
                "is_optional": false
            }
        },
        "new_parameter": {},
        "old_type": "member_function",
        "new_type": "",
        "change_type": "api_removal",
        "IC": "FIC"
    },
    {
        "old_api": "trollimage.colormap.Colormap.to_rio",
        "new_api": "",
        "old_parameter": {
            "self": {
                "description": null,
                "is_optional": false
            }
        },
        "new_parameter": {},
        "old_type": "member_function",
        "new_type": "",
        "change_type": "api_removal",
        "IC": "FIC"
    },
    {
        "old_api": "trollimage.image.Image.__init__",
        "new_api": "",
        "old_parameter": {
            "self": {
                "description": null,
                "is_optional": false
            },
            "channels": {
                "description": null,
                "is_optional": true
            },
            "mode": {
                "description": null,
                "is_optional": true
            },
            "color_range": {
                "description": null,
                "is_optional": true
            },
            "fill_value": {
                "description": null,
                "is_optional": true
            },
            "palette": {
                "description": null,
                "is_optional": true
            },
            "copy": {
                "description": null,
                "is_optional": true
            }
        },
        "new_parameter": {},
        "old_type": "member_function",
        "new_type": "",
        "change_type": "api_removal",
        "IC": "FIC"
    },
    {
        "old_api": "trollimage.image.Image.blend",
        "new_api": "",
        "old_parameter": {
            "self": {
                "description": null,
                "is_optional": false
            },
            "other": {
                "description": null,
                "is_optional": false
            }
        },
        "new_parameter": {},
        "old_type": "member_function",
        "new_type": "",
        "change_type": "api_removal",
        "IC": "FIC"
    },
    {
        "old_api": "trollimage.image.Image.clip",
        "new_api": "",
        "old_parameter": {
            "self": {
                "description": null,
                "is_optional": false
            },
            "channels": {
                "description": null,
                "is_optional": true
            }
        },
        "new_parameter": {},
        "old_type": "member_function",
        "new_type": "",
        "change_type": "api_removal",
        "IC": "FIC"
    },
    {
        "old_api": "trollimage.image.Image.colorize",
        "new_api": "",
        "old_parameter": {
            "self": {
                "description": null,
                "is_optional": false
            },
            "colormap": {
                "description": null,
                "is_optional": false
            }
        },
        "new_parameter": {},
        "old_type": "member_function",
        "new_type": "",
        "change_type": "api_removal",
        "IC": "FIC"
    },
    {
        "old_api": "trollimage.image.Image.convert",
        "new_api": "",
        "old_parameter": {
            "self": {
                "description": null,
                "is_optional": false
            },
            "mode": {
                "description": null,
                "is_optional": false
            }
        },
        "new_parameter": {},
        "old_type": "member_function",
        "new_type": "",
        "change_type": "api_removal",
        "IC": "FIC"
    },
    {
        "old_api": "trollimage.image.Image.crude_stretch",
        "new_api": "",
        "old_parameter": {
            "self": {
                "description": null,
                "is_optional": false
            },
            "ch_nb": {
                "description": null,
                "is_optional": false
            },
            "min_stretch": {
                "description": null,
                "is_optional": true
            },
            "max_stretch": {
                "description": null,
                "is_optional": true
            }
        },
        "new_parameter": {},
        "old_type": "member_function",
        "new_type": "",
        "change_type": "api_removal",
        "IC": "FIC"
    },
    {
        "old_api": "trollimage.image.Image.enhance",
        "new_api": "",
        "old_parameter": {
            "self": {
                "description": null,
                "is_optional": false
            },
            "inverse": {
                "description": null,
                "is_optional": true
            },
            "gamma": {
                "description": null,
                "is_optional": true
            },
            "stretch": {
                "description": null,
                "is_optional": true
            },
            "stretch_parameters": {
                "description": null,
                "is_optional": true
            },
            "kwargs": {
                "description": null,
                "is_optional": false
            }
        },
        "new_parameter": {},
        "old_type": "member_function",
        "new_type": "",
        "change_type": "api_removal",
        "IC": "FIC"
    },
    {
        "old_api": "trollimage.image.Image.gamma",
        "new_api": "",
        "old_parameter": {
            "self": {
                "description": null,
                "is_optional": false
            },
            "gamma": {
                "description": null,
                "is_optional": true
            }
        },
        "new_parameter": {},
        "old_type": "member_function",
        "new_type": "",
        "change_type": "api_removal",
        "IC": "FIC"
    },
    {
        "old_api": "trollimage.image.Image.invert",
        "new_api": "",
        "old_parameter": {
            "self": {
                "description": null,
                "is_optional": false
            },
            "invert": {
                "description": null,
                "is_optional": true
            }
        },
        "new_parameter": {},
        "old_type": "member_function",
        "new_type": "",
        "change_type": "api_removal",
        "IC": "FIC"
    },
    {
        "old_api": "trollimage.image.Image.is_empty",
        "new_api": "",
        "old_parameter": {
            "self": {
                "description": null,
                "is_optional": false
            }
        },
        "new_parameter": {},
        "old_type": "member_function",
        "new_type": "",
        "change_type": "api_removal",
        "IC": "FIC"
    },
    {
        "old_api": "trollimage.image.Image.merge",
        "new_api": "",
        "old_parameter": {
            "self": {
                "description": null,
                "is_optional": false
            },
            "img": {
                "description": null,
                "is_optional": false
            }
        },
        "new_parameter": {},
        "old_type": "member_function",
        "new_type": "",
        "change_type": "api_removal",
        "IC": "FIC"
    },
    {
        "old_api": "trollimage.image.Image.palettize",
        "new_api": "",
        "old_parameter": {
            "self": {
                "description": null,
                "is_optional": false
            },
            "colormap": {
                "description": null,
                "is_optional": false
            }
        },
        "new_parameter": {},
        "old_type": "member_function",
        "new_type": "",
        "change_type": "api_removal",
        "IC": "FIC"
    },
    {
        "old_api": "trollimage.image.Image.pil_image",
        "new_api": "",
        "old_parameter": {
            "self": {
                "description": null,
                "is_optional": false
            }
        },
        "new_parameter": {},
        "old_type": "member_function",
        "new_type": "",
        "change_type": "api_removal",
        "IC": "FIC"
    },
    {
        "old_api": "trollimage.image.Image.pil_save",
        "new_api": "",
        "old_parameter": {
            "self": {
                "description": null,
                "is_optional": false
            },
            "filename": {
                "description": null,
                "is_optional": false
            },
            "compression": {
                "description": null,
                "is_optional": true
            },
            "fformat": {
                "description": null,
                "is_optional": true
            },
            "thumbnail_name": {
                "description": null,
                "is_optional": true
            },
            "thumbnail_size": {
                "description": null,
                "is_optional": true
            }
        },
        "new_parameter": {},
        "old_type": "member_function",
        "new_type": "",
        "change_type": "api_removal",
        "IC": "FIC"
    },
    {
        "old_api": "trollimage.image.Image.putalpha",
        "new_api": "",
        "old_parameter": {
            "self": {
                "description": null,
                "is_optional": false
            },
            "alpha": {
                "description": null,
                "is_optional": false
            }
        },
        "new_parameter": {},
        "old_type": "member_function",
        "new_type": "",
        "change_type": "api_removal",
        "IC": "FIC"
    },
    {
        "old_api": "trollimage.image.Image.replace_luminance",
        "new_api": "",
        "old_parameter": {
            "self": {
                "description": null,
                "is_optional": false
            },
            "luminance": {
                "description": null,
                "is_optional": false
            }
        },
        "new_parameter": {},
        "old_type": "member_function",
        "new_type": "",
        "change_type": "api_removal",
        "IC": "FIC"
    },
    {
        "old_api": "trollimage.image.Image.resize",
        "new_api": "",
        "old_parameter": {
            "self": {
                "description": null,
                "is_optional": false
            },
            "shape": {
                "description": null,
                "is_optional": false
            }
        },
        "new_parameter": {},
        "old_type": "member_function",
        "new_type": "",
        "change_type": "api_removal",
        "IC": "FIC"
    },
    {
        "old_api": "trollimage.image.Image.save",
        "new_api": "",
        "old_parameter": {
            "self": {
                "description": null,
                "is_optional": false
            },
            "filename": {
                "description": null,
                "is_optional": false
            },
            "compression": {
                "description": null,
                "is_optional": true
            },
            "fformat": {
                "description": null,
                "is_optional": true
            },
            "thumbnail_name": {
                "description": null,
                "is_optional": true
            },
            "thumbnail_size": {
                "description": null,
                "is_optional": true
            }
        },
        "new_parameter": {},
        "old_type": "member_function",
        "new_type": "",
        "change_type": "api_removal",
        "IC": "FIC"
    },
    {
        "old_api": "trollimage.image.Image.show",
        "new_api": "",
        "old_parameter": {
            "self": {
                "description": null,
                "is_optional": false
            }
        },
        "new_parameter": {},
        "old_type": "member_function",
        "new_type": "",
        "change_type": "api_removal",
        "IC": "FIC"
    },
    {
        "old_api": "trollimage.image.Image.stretch",
        "new_api": "",
        "old_parameter": {
            "self": {
                "description": null,
                "is_optional": false
            },
            "stretch": {
                "description": null,
                "is_optional": true
            },
            "kwargs": {
                "description": null,
                "is_optional": false
            }
        },
        "new_parameter": {},
        "old_type": "member_function",
        "new_type": "",
        "change_type": "api_removal",
        "IC": "FIC"
    },
    {
        "old_api": "trollimage.image.Image.stretch_hist_equalize",
        "new_api": "",
        "old_parameter": {
            "self": {
                "description": null,
                "is_optional": false
            },
            "ch_nb": {
                "description": null,
                "is_optional": false
            }
        },
        "new_parameter": {},
        "old_type": "member_function",
        "new_type": "",
        "change_type": "api_removal",
        "IC": "FIC"
    },
    {
        "old_api": "trollimage.image.Image.stretch_linear",
        "new_api": "",
        "old_parameter": {
            "self": {
                "description": null,
                "is_optional": false
            },
            "ch_nb": {
                "description": null,
                "is_optional": false
            },
            "cutoffs": {
                "description": null,
                "is_optional": true
            }
        },
        "new_parameter": {},
        "old_type": "member_function",
        "new_type": "",
        "change_type": "api_removal",
        "IC": "FIC"
    },
    {
        "old_api": "trollimage.image.Image.stretch_logarithmic",
        "new_api": "",
        "old_parameter": {
            "self": {
                "description": null,
                "is_optional": false
            },
            "ch_nb": {
                "description": null,
                "is_optional": false
            },
            "factor": {
                "description": null,
                "is_optional": true
            }
        },
        "new_parameter": {},
        "old_type": "member_function",
        "new_type": "",
        "change_type": "api_removal",
        "IC": "FIC"
    },
    {
        "old_api": "trollimage.version.HANDLERS",
        "new_api": "",
        "old_parameter": {},
        "new_parameter": {},
        "old_type": "module_field",
        "new_type": "",
        "change_type": "api_removal",
        "IC": "FIC"
    },
    {
        "old_api": "trollimage.version.LONG_VERSION_PY",
        "new_api": "",
        "old_parameter": {},
        "new_parameter": {},
        "old_type": "module_field",
        "new_type": "",
        "change_type": "api_removal",
        "IC": "FIC"
    },
    {
        "old_api": "trollimage.version.NotThisMethod",
        "new_api": "",
        "old_parameter": {},
        "new_parameter": {},
        "old_type": "class",
        "new_type": "",
        "change_type": "api_removal",
        "IC": "FIC"
    },
    {
        "old_api": "trollimage.version.VersioneerConfig",
        "new_api": "",
        "old_parameter": {},
        "new_parameter": {},
        "old_type": "class",
        "new_type": "",
        "change_type": "api_removal",
        "IC": "FIC"
    },
    {
        "old_api": "trollimage.version.get_config",
        "new_api": "",
        "old_parameter": {},
        "new_parameter": {},
        "old_type": "function",
        "new_type": "",
        "change_type": "api_removal",
        "IC": "FIC"
    },
    {
        "old_api": "trollimage.version.get_keywords",
        "new_api": "",
        "old_parameter": {},
        "new_parameter": {},
        "old_type": "function",
        "new_type": "",
        "change_type": "api_removal",
        "IC": "FIC"
    },
    {
        "old_api": "trollimage.version.git_get_keywords",
        "new_api": "",
        "old_parameter": {
            "versionfile_abs": {
                "description": null,
                "is_optional": false
            }
        },
        "new_parameter": {},
        "old_type": "function",
        "new_type": "",
        "change_type": "api_removal",
        "IC": "FIC"
    },
    {
        "old_api": "trollimage.version.git_pieces_from_vcs",
        "new_api": "",
        "old_parameter": {
            "tag_prefix": {
                "description": null,
                "is_optional": false
            },
            "root": {
                "description": null,
                "is_optional": false
            },
            "verbose": {
                "description": null,
                "is_optional": false
            },
            "run_command": {
                "description": null,
                "is_optional": true
            }
        },
        "new_parameter": {},
        "old_type": "function",
        "new_type": "",
        "change_type": "api_removal",
        "IC": "FIC"
    },
    {
        "old_api": "trollimage.version.git_versions_from_keywords",
        "new_api": "",
        "old_parameter": {
            "keywords": {
                "description": null,
                "is_optional": false
            },
            "tag_prefix": {
                "description": null,
                "is_optional": false
            },
            "verbose": {
                "description": null,
                "is_optional": false
            }
        },
        "new_parameter": {},
        "old_type": "function",
        "new_type": "",
        "change_type": "api_removal",
        "IC": "FIC"
    },
    {
        "old_api": "trollimage.version.plus_or_dot",
        "new_api": "",
        "old_parameter": {
            "pieces": {
                "description": null,
                "is_optional": false
            }
        },
        "new_parameter": {},
        "old_type": "function",
        "new_type": "",
        "change_type": "api_removal",
        "IC": "FIC"
    },
    {
        "old_api": "trollimage.version.register_vcs_handler",
        "new_api": "",
        "old_parameter": {
            "vcs": {
                "description": null,
                "is_optional": false
            },
            "method": {
                "description": null,
                "is_optional": false
            }
        },
        "new_parameter": {},
        "old_type": "function",
        "new_type": "",
        "change_type": "api_removal",
        "IC": "FIC"
    },
    {
        "old_api": "trollimage.version.render",
        "new_api": "",
        "old_parameter": {
            "pieces": {
                "description": null,
                "is_optional": false
            },
            "style": {
                "description": null,
                "is_optional": false
            }
        },
        "new_parameter": {},
        "old_type": "function",
        "new_type": "",
        "change_type": "api_removal",
        "IC": "FIC"
    },
    {
        "old_api": "trollimage.version.render_git_describe",
        "new_api": "",
        "old_parameter": {
            "pieces": {
                "description": null,
                "is_optional": false
            }
        },
        "new_parameter": {},
        "old_type": "function",
        "new_type": "",
        "change_type": "api_removal",
        "IC": "FIC"
    },
    {
        "old_api": "trollimage.version.render_git_describe_long",
        "new_api": "",
        "old_parameter": {
            "pieces": {
                "description": null,
                "is_optional": false
            }
        },
        "new_parameter": {},
        "old_type": "function",
        "new_type": "",
        "change_type": "api_removal",
        "IC": "FIC"
    },
    {
        "old_api": "trollimage.version.render_pep440",
        "new_api": "",
        "old_parameter": {
            "pieces": {
                "description": null,
                "is_optional": false
            }
        },
        "new_parameter": {},
        "old_type": "function",
        "new_type": "",
        "change_type": "api_removal",
        "IC": "FIC"
    },
    {
        "old_api": "trollimage.version.render_pep440_old",
        "new_api": "",
        "old_parameter": {
            "pieces": {
                "description": null,
                "is_optional": false
            }
        },
        "new_parameter": {},
        "old_type": "function",
        "new_type": "",
        "change_type": "api_removal",
        "IC": "FIC"
    },
    {
        "old_api": "trollimage.version.render_pep440_post",
        "new_api": "",
        "old_parameter": {
            "pieces": {
                "description": null,
                "is_optional": false
            }
        },
        "new_parameter": {},
        "old_type": "function",
        "new_type": "",
        "change_type": "api_removal",
        "IC": "FIC"
    },
    {
        "old_api": "trollimage.version.render_pep440_pre",
        "new_api": "",
        "old_parameter": {
            "pieces": {
                "description": null,
                "is_optional": false
            }
        },
        "new_parameter": {},
        "old_type": "function",
        "new_type": "",
        "change_type": "api_removal",
        "IC": "FIC"
    },
    {
        "old_api": "trollimage.version.run_command",
        "new_api": "",
        "old_parameter": {
            "commands": {
                "description": null,
                "is_optional": false
            },
            "args": {
                "description": null,
                "is_optional": false
            },
            "cwd": {
                "description": null,
                "is_optional": true
            },
            "verbose": {
                "description": null,
                "is_optional": true
            },
            "hide_stderr": {
                "description": null,
                "is_optional": true
            },
            "env": {
                "description": null,
                "is_optional": true
            }
        },
        "new_parameter": {},
        "old_type": "function",
        "new_type": "",
        "change_type": "api_removal",
        "IC": "FIC"
    },
    {
        "old_api": "trollimage.version.versions_from_parentdir",
        "new_api": "",
        "old_parameter": {
            "parentdir_prefix": {
                "description": null,
                "is_optional": false
            },
            "root": {
                "description": null,
                "is_optional": false
            },
            "verbose": {
                "description": null,
                "is_optional": false
            }
        },
        "new_parameter": {},
        "old_type": "function",
        "new_type": "",
        "change_type": "api_removal",
        "IC": "FIC"
    },
    {
        "old_api": "trollimage.image.six",
        "new_api": "",
        "old_parameter": {},
        "new_parameter": {},
        "old_type": "dir api",
        "new_type": "",
        "change_type": "api_removal",
        "IC": "FIC"
    },
    {
        "old_api": "trollimage.version.errno",
        "new_api": "",
        "old_parameter": {},
        "new_parameter": {},
        "old_type": "dir api",
        "new_type": "",
        "change_type": "api_removal",
        "IC": "FIC"
    },
    {
        "old_api": "trollimage.version.os",
        "new_api": "",
        "old_parameter": {},
        "new_parameter": {},
        "old_type": "dir api",
        "new_type": "",
        "change_type": "api_removal",
        "IC": "FIC"
    },
    {
        "old_api": "trollimage.version.re",
        "new_api": "",
        "old_parameter": {},
        "new_parameter": {},
        "old_type": "dir api",
        "new_type": "",
        "change_type": "api_removal",
        "IC": "FIC"
    },
    {
        "old_api": "trollimage.version.subprocess",
        "new_api": "",
        "old_parameter": {},
        "new_parameter": {},
        "old_type": "dir api",
        "new_type": "",
        "change_type": "api_removal",
        "IC": "FIC"
    },
    {
        "old_api": "trollimage.version.sys",
        "new_api": "",
        "old_parameter": {},
        "new_parameter": {},
        "old_type": "dir api",
        "new_type": "",
        "change_type": "api_removal",
        "IC": "FIC"
    },
    {
        "old_api": "",
        "new_api": "trollimage.version.version_json",
        "old_parameter": {},
        "new_parameter": {},
        "old_type": "",
        "new_type": "module_field",
        "change_type": "api_addition",
        "IC": "BIC"
    },
    {
        "old_api": "",
        "new_api": "trollimage.colormap.Number",
        "old_parameter": {},
        "new_parameter": {},
        "old_type": "",
        "new_type": "dir api",
        "change_type": "api_addition",
        "IC": "BIC"
    },
    {
        "old_api": "",
        "new_api": "trollimage.colormap.Optional",
        "old_parameter": {},
        "new_parameter": {},
        "old_type": "",
        "new_type": "dir api",
        "change_type": "api_addition",
        "IC": "BIC"
    },
    {
        "old_api": "",
        "new_api": "trollimage.colormap.StringIO",
        "old_parameter": {},
        "new_parameter": {},
        "old_type": "",
        "new_type": "dir api",
        "change_type": "api_addition",
        "IC": "BIC"
    },
    {
        "old_api": "",
        "new_api": "trollimage.colormap._colorize",
        "old_parameter": {},
        "new_parameter": {},
        "old_type": "",
        "new_type": "dir api",
        "change_type": "api_addition",
        "IC": "BIC"
    },
    {
        "old_api": "",
        "new_api": "trollimage.colormap._colorize_dask",
        "old_parameter": {},
        "new_parameter": {},
        "old_type": "",
        "new_type": "dir api",
        "change_type": "api_addition",
        "IC": "BIC"
    },
    {
        "old_api": "",
        "new_api": "trollimage.colormap._convert_rgb_list_to_hcl",
        "old_parameter": {},
        "new_parameter": {},
        "old_type": "",
        "new_type": "dir api",
        "change_type": "api_addition",
        "IC": "BIC"
    },
    {
        "old_api": "",
        "new_api": "trollimage.colormap._digitize_array",
        "old_parameter": {},
        "new_parameter": {},
        "old_type": "",
        "new_type": "dir api",
        "change_type": "api_addition",
        "IC": "BIC"
    },
    {
        "old_api": "",
        "new_api": "trollimage.colormap._file_or_stringio",
        "old_parameter": {},
        "new_parameter": {},
        "old_type": "",
        "new_type": "dir api",
        "change_type": "api_addition",
        "IC": "BIC"
    },
    {
        "old_api": "",
        "new_api": "trollimage.colormap._get_values_colors_from_file",
        "old_parameter": {},
        "new_parameter": {},
        "old_type": "",
        "new_type": "dir api",
        "change_type": "api_addition",
        "IC": "BIC"
    },
    {
        "old_api": "",
        "new_api": "trollimage.colormap._get_values_colors_from_ndarray",
        "old_parameter": {},
        "new_parameter": {},
        "old_type": "",
        "new_type": "dir api",
        "change_type": "api_addition",
        "IC": "BIC"
    },
    {
        "old_api": "",
        "new_api": "trollimage.colormap._interpolate_alpha",
        "old_parameter": {},
        "new_parameter": {},
        "old_type": "",
        "new_type": "dir api",
        "change_type": "api_addition",
        "IC": "BIC"
    },
    {
        "old_api": "",
        "new_api": "trollimage.colormap._interpolate_rgb_colors",
        "old_parameter": {},
        "new_parameter": {},
        "old_type": "",
        "new_type": "dir api",
        "change_type": "api_addition",
        "IC": "BIC"
    },
    {
        "old_api": "",
        "new_api": "trollimage.colormap._is_actually_a_csv_string",
        "old_parameter": {},
        "new_parameter": {},
        "old_type": "",
        "new_type": "dir api",
        "change_type": "api_addition",
        "IC": "BIC"
    },
    {
        "old_api": "",
        "new_api": "trollimage.colormap._mask_array",
        "old_parameter": {},
        "new_parameter": {},
        "old_type": "",
        "new_type": "dir api",
        "change_type": "api_addition",
        "IC": "BIC"
    },
    {
        "old_api": "",
        "new_api": "trollimage.colormap._mask_channels",
        "old_parameter": {},
        "new_parameter": {},
        "old_type": "",
        "new_type": "dir api",
        "change_type": "api_addition",
        "IC": "BIC"
    },
    {
        "old_api": "",
        "new_api": "trollimage.colormap._palettize",
        "old_parameter": {},
        "new_parameter": {},
        "old_type": "",
        "new_type": "dir api",
        "change_type": "api_addition",
        "IC": "BIC"
    },
    {
        "old_api": "",
        "new_api": "trollimage.colormap._palettize_dask",
        "old_parameter": {},
        "new_parameter": {},
        "old_type": "",
        "new_type": "dir api",
        "change_type": "api_addition",
        "IC": "BIC"
    },
    {
        "old_api": "",
        "new_api": "trollimage.colormap._read_colormap_data_from_file",
        "old_parameter": {},
        "new_parameter": {},
        "old_type": "",
        "new_type": "dir api",
        "change_type": "api_addition",
        "IC": "BIC"
    },
    {
        "old_api": "",
        "new_api": "trollimage.colormap._read_colormap_data_from_np",
        "old_parameter": {},
        "new_parameter": {},
        "old_type": "",
        "new_type": "dir api",
        "change_type": "api_addition",
        "IC": "BIC"
    },
    {
        "old_api": "",
        "new_api": "trollimage.colormap._unwrap_colors_in_hcl_space",
        "old_parameter": {},
        "new_parameter": {},
        "old_type": "",
        "new_type": "dir api",
        "change_type": "api_addition",
        "IC": "BIC"
    },
    {
        "old_api": "",
        "new_api": "trollimage.colormap.can_be_block_mapped",
        "old_parameter": {},
        "new_parameter": {},
        "old_type": "",
        "new_type": "dir api",
        "change_type": "api_addition",
        "IC": "BIC"
    },
    {
        "old_api": "",
        "new_api": "trollimage.colormap.contextlib",
        "old_parameter": {},
        "new_parameter": {},
        "old_type": "",
        "new_type": "dir api",
        "change_type": "api_addition",
        "IC": "BIC"
    },
    {
        "old_api": "",
        "new_api": "trollimage.colormap.copy",
        "old_parameter": {},
        "new_parameter": {},
        "old_type": "",
        "new_type": "dir api",
        "change_type": "api_addition",
        "IC": "BIC"
    },
    {
        "old_api": "",
        "new_api": "trollimage.colormap.os",
        "old_parameter": {},
        "new_parameter": {},
        "old_type": "",
        "new_type": "dir api",
        "change_type": "api_addition",
        "IC": "BIC"
    },
    {
        "old_api": "",
        "new_api": "trollimage.colormap.pathlib",
        "old_parameter": {},
        "new_parameter": {},
        "old_type": "",
        "new_type": "dir api",
        "change_type": "api_addition",
        "IC": "BIC"
    },
    {
        "old_api": "",
        "new_api": "trollimage.colormap.sys",
        "old_parameter": {},
        "new_parameter": {},
        "old_type": "",
        "new_type": "dir api",
        "change_type": "api_addition",
        "IC": "BIC"
    },
    {
        "old_api": "",
        "new_api": "trollimage.colormap.warnings",
        "old_parameter": {},
        "new_parameter": {},
        "old_type": "",
        "new_type": "dir api",
        "change_type": "api_addition",
        "IC": "BIC"
    },
    {
        "old_api": "",
        "new_api": "trollimage.image._pprint_pil_formats",
        "old_parameter": {},
        "new_parameter": {},
        "old_type": "",
        "new_type": "dir api",
        "change_type": "api_addition",
        "IC": "BIC"
    },
    {
        "old_api": "",
        "new_api": "trollimage.image.get_pillow_image_formats",
        "old_parameter": {},
        "new_parameter": {},
        "old_type": "",
        "new_type": "dir api",
        "change_type": "api_addition",
        "IC": "BIC"
    },
    {
        "old_api": "",
        "new_api": "trollimage.image.lru_cache",
        "old_parameter": {},
        "new_parameter": {},
        "old_type": "",
        "new_type": "dir api",
        "change_type": "api_addition",
        "IC": "BIC"
    },
    {
        "old_api": "",
        "new_api": "trollimage.utilities.Colormap",
        "old_parameter": {},
        "new_parameter": {},
        "old_type": "",
        "new_type": "dir api",
        "change_type": "api_addition",
        "IC": "BIC"
    },
    {
        "old_api": "",
        "new_api": "trollimage.utilities.Image",
        "old_parameter": {},
        "new_parameter": {},
        "old_type": "",
        "new_type": "dir api",
        "change_type": "api_addition",
        "IC": "BIC"
    },
    {
        "old_api": "",
        "new_api": "trollimage.utilities.Pimage",
        "old_parameter": {},
        "new_parameter": {},
        "old_type": "",
        "new_type": "dir api",
        "change_type": "api_addition",
        "IC": "BIC"
    },
    {
        "old_api": "",
        "new_api": "trollimage.utilities._hex_to_rgb",
        "old_parameter": {},
        "new_parameter": {},
        "old_type": "",
        "new_type": "dir api",
        "change_type": "api_addition",
        "IC": "BIC"
    },
    {
        "old_api": "",
        "new_api": "trollimage.utilities._image2array",
        "old_parameter": {},
        "new_parameter": {},
        "old_type": "",
        "new_type": "dir api",
        "change_type": "api_addition",
        "IC": "BIC"
    },
    {
        "old_api": "",
        "new_api": "trollimage.utilities._make_cmap",
        "old_parameter": {},
        "new_parameter": {},
        "old_type": "",
        "new_type": "dir api",
        "change_type": "api_addition",
        "IC": "BIC"
    },
    {
        "old_api": "",
        "new_api": "trollimage.utilities._text_to_rgb",
        "old_parameter": {},
        "new_parameter": {},
        "old_type": "",
        "new_type": "dir api",
        "change_type": "api_addition",
        "IC": "BIC"
    },
    {
        "old_api": "",
        "new_api": "trollimage.utilities.cmap_from_text",
        "old_parameter": {},
        "new_parameter": {},
        "old_type": "",
        "new_type": "dir api",
        "change_type": "api_addition",
        "IC": "BIC"
    },
    {
        "old_api": "",
        "new_api": "trollimage.utilities.division",
        "old_parameter": {},
        "new_parameter": {},
        "old_type": "",
        "new_type": "dir api",
        "change_type": "api_addition",
        "IC": "BIC"
    },
    {
        "old_api": "",
        "new_api": "trollimage.utilities.np",
        "old_parameter": {},
        "new_parameter": {},
        "old_type": "",
        "new_type": "dir api",
        "change_type": "api_addition",
        "IC": "BIC"
    },
    {
        "old_api": "",
        "new_api": "trollimage.utilities.pilimage2trollimage",
        "old_parameter": {},
        "new_parameter": {},
        "old_type": "",
        "new_type": "dir api",
        "change_type": "api_addition",
        "IC": "BIC"
    },
    {
        "old_api": "",
        "new_api": "trollimage.utilities.sys",
        "old_parameter": {},
        "new_parameter": {},
        "old_type": "",
        "new_type": "dir api",
        "change_type": "api_addition",
        "IC": "BIC"
    },
    {
        "old_api": "",
        "new_api": "trollimage.version.json",
        "old_parameter": {},
        "new_parameter": {},
        "old_type": "",
        "new_type": "dir api",
        "change_type": "api_addition",
        "IC": "BIC"
    }
]